kanshipy-0.0.1.dist-info/METADATA
kanshipy-0.0.1.dist-info/WHEEL
kanshipy-0.0.1.dist-info/licenses/LICENSE
kanshipy/__init__.py
kanshipy/_kanshipy.pypy310-pp73-x86_64-linux-gnu.so
kanshipy-0.0.1.dist-info/RECORD
