Metadata-Version: 2.4
Name: kanshipy
Version: 0.0.1
Classifier: Programming Language :: Rust
Classifier: Programming Language :: Python :: Implementation :: CPython
Classifier: Programming Language :: Python :: Implementation :: PyPy
License-File: LICENSE
Summary: A high level abstraction above native file system watcher APIs (like inotify, fanotify, etc)
Home-Page: https://github.com/carlvoller/kanshi
Author: Carl Voller
License: BSD-3-Clause
Requires-Python: >=3.8
Project-URL: Source Code, https://github.com/carlvoller/kanshi
